{
  "projects": [
    {
      "name": "Iate Clube de Fortaleza",
      "budget": "5.000",
      "category": {
        "id": "4",
        "name": "Planejamento"
      },
      "cost": null,
      "services": [
        {
          "id": "9ca80982-37d7-4321-a337-21e14a3db7d5"
        },
        {
          "id": "fea6bf6d-cf91-4c88-be5d-b2136f0e7c2e"
        },
        {
          "id": "02f354b3-be1d-45f2-945a-1c0a32859278"
        },
        {
          "id": "02f354b3-be1d-45f2-945a-1c0a32859278"
        },
        {
          "id": "02f354b3-be1d-45f2-945a-1c0a32859278"
        },
        {
          "id": "02f354b3-be1d-45f2-945a-1c0a32859278"
        },
        {
          "id": "34788d5a-b1be-42fe-8375-fdd8ad4011ba"
        },
        {
          "id": "34788d5a-b1be-42fe-8375-fdd8ad4011ba"
        },
        {
          "id": "34788d5a-b1be-42fe-8375-fdd8ad4011ba"
        },
        {
          "id": "a483cd48-9577-4ae9-8e4a-2079271a0048"
        },
        {
          "id": "37fe3a61-e42b-471d-a014-571d9f7bec78"
        },
        {
          "id": "1cd5e13a-a5fe-467f-abc5-a43a3544342e"
        }
      ],
      "id": 1
    },
    {
      "name": "Rotary Club",
      "budget": "30.000",
      "category": {
        "id": "2",
        "name": "Desenvolvimento"
      },
      "cost": 0,
      "services": [],
      "id": 2
    },
    {
      "name": "Club Vela",
      "budget": "22.000",
      "category": {
        "id": "1",
        "name": "Infra"
      },
      "cost": 0,
      "services": [],
      "id": 3
    }
  ],
  "categories": [
    {
      "id": 1,
      "name": "Infra"
    },
    {
      "id": 2,
      "name": "Desenvolvimento"
    },
    {
      "id": 3,
      "name": "Design"
    },
    {
      "id": 4,
      "name": "Planejamento"
    }
  ]
}